tusker/__init__.py
tusker/config.py
tusker-0.5.1.dist-info/LICENSE
tusker-0.5.1.dist-info/METADATA
tusker-0.5.1.dist-info/WHEEL
tusker-0.5.1.dist-info/entry_points.txt
tusker-0.5.1.dist-info/RECORD
