Metadata-Version: 2.1
Name: tusker
Version: 0.5.1
Summary: A PostgreSQL specific migration tool
Home-page: https://github.com/bikeshedder/tusker
License: Unlicense
Author: Michael P. Jung
Author-email: michael.jung@terreon.de
Requires-Python: >=3.7,<4.0
Classifier: Development Status :: 4 - Beta
Classifier: License :: Other/Proprietary License
Classifier: Programming Language :: Python
Classifier: Programming Language :: Python :: 3
Classifier: Programming Language :: Python :: 3.7
Classifier: Programming Language :: Python :: 3.8
Classifier: Programming Language :: Python :: 3.9
Classifier: Programming Language :: Python :: 3.10
Classifier: Programming Language :: Python :: 3.11
Classifier: Programming Language :: Python :: 3
Classifier: Programming Language :: Python :: 3 :: Only
Classifier: Topic :: Database
Classifier: Topic :: Utilities
Requires-Dist: importlib-metadata (>=1.0,<2.0) ; python_version < "3.8"
Requires-Dist: migra (>=3.0.1621480950,<4.0.0)
Requires-Dist: psycopg2 (>=2.9.5,<3.0.0)
Requires-Dist: sqlalchemy (>=1.4.25,<2.0.0)
Requires-Dist: tomlkit (>=0.11,<0.12)
Project-URL: Repository, https://github.com/bikeshedder/tusker
